CHANGES.txt
README.txt
bootstrap.py
buildout.cfg
setup.py
docs/LICENSE.txt
src/__init__.py
src/Products/__init__.py
src/Products.PloneFlashUpload.egg-info/PKG-INFO
src/Products.PloneFlashUpload.egg-info/SOURCES.txt
src/Products.PloneFlashUpload.egg-info/dependency_links.txt
src/Products.PloneFlashUpload.egg-info/namespace_packages.txt
src/Products.PloneFlashUpload.egg-info/not-zip-safe
src/Products.PloneFlashUpload.egg-info/requires.txt
src/Products.PloneFlashUpload.egg-info/top_level.txt
src/Products/PloneFlashUpload/__init__.py
src/Products/PloneFlashUpload/atct.py
src/Products/PloneFlashUpload/browser.py
src/Products/PloneFlashUpload/configlet.pt
src/Products/PloneFlashUpload/configure.zcml
src/Products/PloneFlashUpload/flashuploadvars.pt
src/Products/PloneFlashUpload/functional.txt
src/Products/PloneFlashUpload/interfaces.py
src/Products/PloneFlashUpload/ploneflashupload.css
src/Products/PloneFlashUpload/ploneflashupload.js
src/Products/PloneFlashUpload/setuphandlers.py
src/Products/PloneFlashUpload/success.pt
src/Products/PloneFlashUpload/tests.py
src/Products/PloneFlashUpload/ticket.py
src/Products/PloneFlashUpload/uploadform.pt
src/Products/PloneFlashUpload/utils.py
src/Products/PloneFlashUpload/profiles/default/actionicons.xml
src/Products/PloneFlashUpload/profiles/default/actions.xml
src/Products/PloneFlashUpload/profiles/default/contenttyperegistry.xml
src/Products/PloneFlashUpload/profiles/default/controlpanel.xml
src/Products/PloneFlashUpload/profiles/default/metadata.xml
src/Products/PloneFlashUpload/profiles/default/ploneflashupload.txt
src/Products/PloneFlashUpload/swfupload/cookies.js
src/Products/PloneFlashUpload/swfupload/fileprogress.js
src/Products/PloneFlashUpload/swfupload/handlers.js
src/Products/PloneFlashUpload/swfupload/queue.js
src/Products/PloneFlashUpload/swfupload/swfobject.js
src/Products/PloneFlashUpload/swfupload/swfupload.js
src/Products/PloneFlashUpload/swfupload/swfupload.swf