Metadata-Version: 1.0
Name: Products.PloneFlashUpload
Version: 1.3
Summary: Add-on that allows mass-upload of files and images.
Home-page: http://plone.org/products/ploneflashupload
Author: Rocky Burt (3.0 support by Reinout van Rees)
Author-email: reinout@zestsoftware.nl
License: Zope Public License (ZPL) Version 2.1
Keywords: plone upload images
Platform: UNKNOWN
Classifier: Framework :: Plone
Classifier: Programming Language :: Python
